log_metrics
