Metadata-Version: 1.1
Name: log-metrics
Version: 0.0.4
Summary: Python Metric Logger.
Home-page: https://github.com/rhyselsmore/log-metrics
Author: Rhys Elsmore
Author-email: me@rhys.io
License: Apache 2.0
Platform: UNKNOWN
Classifier: Development Status :: 5 - Production/Stable
Classifier: Intended Audience :: Developers
Classifier: Natural Language :: English
Classifier: License :: OSI Approved :: Apache Software License
Classifier: Programming Language :: Python
Classifier: Programming Language :: Python :: 2.6
Classifier: Programming Language :: Python :: 2.7
Classifier: Programming Language :: Python :: 3
Classifier: Programming Language :: Python :: 3.3
